etlx/__init__.py
etlx/build.py
etlx/factory.py
etlx/abc/__init__.py
etlx/abc/column.py
etlx/abc/index.py
etlx/abc/mapper.py
etlx/abc/metadata.py
etlx/abc/row.py
etlx/abc/table.py
etlx/dbi/__init__.py
etlx/dbi/abc.py
etlx/dbi/mysql/__init__.py
etlx/dbi/mysql/dbi_mysqldb.py
etlx/dbi/mysql/metadata.py
etlx/dbi/postgres/__init__.py
etlx/dbi/postgres/dbi_psycopg2.py
etlx/dbi/sqlite/__init__.py
etlx/dbi/sqlite/dbi_sqlite3.py
etlx/sql/__init__.py
etlx/sql/sql.py
etlx/sql/parse/__init__.py
etlx/sql/parse/lexer.py
etlx-0.0.7.dist-info/LICENSE
etlx-0.0.7.dist-info/METADATA
etlx-0.0.7.dist-info/WHEEL
etlx-0.0.7.dist-info/top_level.txt
etlx-0.0.7.dist-info/RECORD
