Metadata-Version: 2.1
Name: etlx
Version: 0.0.7
Summary: ETL & Co
Home-page: https://github.com/kedikx/etlx
Author: Alexander Keda
Author-email: kedikx.io@gmail.com
License: UNKNOWN
Platform: UNKNOWN
Classifier: Programming Language :: Python :: 3
Classifier: Programming Language :: Python :: 3.6
Classifier: Programming Language :: Python :: 3.7
Classifier: Programming Language :: Python :: 3.8
Classifier: License :: OSI Approved :: MIT License
Classifier: Operating System :: OS Independent
Requires-Dist: PyYAML
Provides-Extra: mysql
Requires-Dist: mysqlclient ; extra == 'mysql'
Provides-Extra: postgres
Requires-Dist: psycopg2 ; extra == 'postgres'
